Tarea 1/src/tester.v
module tester (/*AUTOARG*/

            // Outputs
            clock, reset
            );

            output reg clock;
            output reg reset;

            initial begin 
              clock = 0;
              reset = 0;
              #10 reset = 1;  //Reset en 10s

              #20 reset = 0;
              #10 reset = 1;

	      #950 reset = 0;
	      #10 reset = 1; 

	      #650 reset = 0;
	      #10 reset = 1;



              #700 $finish;  //Termina la simulación a los 2000 segundos
            end

            always begin
              #10 clock = !clock;
            end

endmodule

Tarea 1/src/cpu.v
module cpu ( /*AUTOOUTPUT*/
             /*AUTOARG*/
            // Inputs
            clock, reset, opcode, ab_select, op_addr, mem_data_in,

            //Outputs
              prog_addr, mem_control, mem_addr, equal, mem_data_out, request_rom, request_ram
            );

//Inputs   
input clock, reset;
input [3:0]opcode;   // Puede ser un parametro
input ab_select;     // Puede ser un parametro
input [7:0]op_addr;  // Puede ser un parametro 
input [7:0]mem_data_in;

//Outputs
output reg [11:0]prog_addr;
output reg mem_control;
output reg [11:0]mem_addr;
output reg equal, request_rom, request_ram;
output reg [7:0]mem_data_out;

//States
localparam send_ROM = 4'b0000;
localparam wait_ROM = 4'b0001;
localparam read_ROM = 4'b0010;
localparam logic_operation = 4'b0011;
localparam Instruction = 4'b0100;
localparam wait_RAM = 4'b0101;
localparam load_register = 4'b0110;
localparam End =4'b0111;
// 4'b1000;

//Operations
localparam store = 4'b0100;
localparam load  = 4'b0011;
localparam add   = 4'b1001;
localparam sub   = 4'b1010;
localparam and_  = 4'b0010;
localparam or_   = 4'b0001;
localparam equal_operation = 4'b0101;

//Declaración de variables para los estados
reg [3:0] state, next_state;
reg [7:0] A, next_A, B, next_B;

//Reg para recibir datos
reg reg_ab_select, reg_ab_select_next; 
reg [3:0] reg_opcode, reg_opcode_next;
reg [7:0] reg_op_addr, reg_op_addr_next;

reg mem_control_next, request_rom_next, request_ram_next, equal_next;
reg [11:0] mem_addr_next;
reg [11:0] prog_addr_next;
reg [7:0] mem_data_out_next;


// Lógica secuencial(flip-flops)
always @(posedge clock) begin
  if (!reset) begin   //Reset=0, se hace todo cero y comienza en send_ROM.
    state <= send_ROM;
    prog_addr <= 12'b0;
    mem_control <= 0;
    mem_addr <= 12'b0;
    mem_data_out <= 8'b0;
    equal <= 0;
    A <= 8'b0;
    B <= 8'b0;
    request_rom <= 0;
    request_ram <= 0;
    reg_opcode <= 4'b0;
    reg_ab_select <= 0;
    reg_op_addr <= 8'b0;
  end else begin    //Reset=1, sigue la lógica de la maquina de estados. 
    state <= next_state;
    mem_control <= mem_control_next;
    mem_addr <= mem_addr_next;
    mem_data_out <=mem_data_out_next;
    equal <= equal_next;
    A <= next_A;
    B <= next_B;
    request_rom <= request_rom_next;
    request_ram <= request_ram_next;
    reg_opcode <= reg_opcode_next;
    reg_ab_select <= reg_ab_select_next;
    reg_op_addr <= reg_op_addr_next;
    prog_addr <= prog_addr_next;
  end
end


// Lógica combinacional 
always @(*) begin 
  // Valores por defecto a la hora de inciar 
  next_state = state;
  next_A = A;
  next_B = B;
  mem_control_next = mem_control;
  mem_addr_next = mem_addr;
  mem_data_out_next = mem_data_out;
  request_rom_next = 0;
  request_ram_next = 0;
  reg_opcode_next = reg_opcode;
  reg_ab_select_next = reg_ab_select;
  reg_op_addr_next = reg_op_addr;
  equal_next = equal;
  prog_addr_next = prog_addr;

  //Máquina de estados
  case (state)
    //Estado 0 = Solicitar la instrucción a la ROM. 
    send_ROM: begin
      request_rom_next = 1;   //Activa la señal que solicita info a la Rom.
      next_state = wait_ROM;  //Pasa al próximo estado.
    end
    
    //Estado 1 = Esoera a que la ROM entregue los datos. 
    wait_ROM: begin
      request_rom_next = 1;   //Espera un ciclo de clock para que la ROM responda. 
      next_state = read_ROM;
    end
    
    //Estado 2 = Lee la instrucción que llega de la ROm 
    read_ROM: begin
      reg_opcode_next = opcode;
      reg_ab_select_next = ab_select;
      reg_op_addr_next = op_addr;

      //prog_addr_next = prog_addr + 1;  //Incrementa el contador de intrucciones

      case (opcode)
        load, store: next_state = Instruction;
	equal_operation: next_state = logic_operation;
        default: next_state = logic_operation;
      endcase
    end


    //Estado 3 = Operaciones lógicas 
    logic_operation: begin
      case (reg_opcode)
        add: begin
          if (reg_ab_select) 
            next_A = A + B;
          else 
            next_B = A + B;
            next_state = send_ROM;
	    prog_addr_next = prog_addr + 1;
        end

        sub: begin 
          if (reg_ab_select) 
            next_A = A - B;
          else 
            next_B = A - B;
            next_state = send_ROM;
	    prog_addr_next = prog_addr + 1;
        end

        and_: begin 
          if (reg_ab_select)
            next_A = A & B;
          else
            next_B = A & B;
            next_state = send_ROM;
	    prog_addr_next = prog_addr + 1; 
        end

        or_: begin
          if (reg_ab_select)
            next_A = A | B;
          else
            next_B = A | B;
            next_state = send_ROM;
	    prog_addr_next = prog_addr + 1;
        end

        equal_operation: begin 
          equal_next = (A == B);
          next_state = End;
        end
        default: next_state = send_ROM;
      endcase
    end


    //Estado 4 = Acceso a la memoria RAM.
    Instruction: begin
      request_ram_next = 1;
      mem_addr_next = {4'b0, reg_op_addr};

      if (reg_opcode == load) begin
        mem_control_next = 1;   //Indica que se va hacer lectura.
        next_state = wait_RAM;
      end
      else begin
        mem_control_next = 0;  //Indica que se va hacer escritura.
	mem_data_out_next = (reg_ab_select)? B:A;
	next_state = wait_RAM;

        end 
      end


      //Estado 5 = Esperar el acceso a la RAM.
      wait_RAM: begin
        request_ram_next = 1;
            if (reg_opcode == load) next_state = load_register;
            else begin
                next_state = send_ROM;
                prog_addr_next = prog_addr + 1;
            end
        end


      //Estado 6 = Cargar el dato en la RAM.
      load_register: begin 
        if (reg_ab_select) next_B = mem_data_in;
          else next_A = mem_data_in;
	  next_state = send_ROM;
	  prog_addr_next = prog_addr + 1;
        end
        

        //Estado = Fin del programa.
        End: begin
          next_state = End; //Mantiene el programa en el estado que termina todo
	  //request_rom = 0;
	  //request_ram = 0; 
        end
        default: next_state = send_ROM;
    endcase
end


endmodule

Tarea 1/src/ram.v
module ram (/*AUTOARG*/
   //Inputs
    clock, reset, request_ram, mem_control, mem_addr, mem_data_out,
   
   //Outputs
    mem_data_in
    );

    input  clock, reset, request_ram, mem_control;
    input [11:0] mem_addr;
    input [7:0] mem_data_out;
    output reg [7:0] mem_data_in;

    localparam write = 0;
    localparam read = 1;

    reg [7:0] memory [0:31];  //Declaración del arreglo 
    integer i;


    initial begin
      // Inicializa todo a 0
        for (i = 0; i < 32; i = i + 1) memory[i] = 8'b0;  //Inicializar todo en 0

      //Mi carnet es C27645
      memory[0] = 8'd7;  // Primer dígito
      memory[1] = 8'd6;  // Segundo dígito
      memory[2] = 8'd4;  // Tercer dígito
      memory[3] = 8'd5;  // Cuarto dígito 
      memory[5]  = 8'd12; // Valor para LOAD A from 005
      // Espacios en 0
      memory[10] = 8'd13; // Valor para LOAD B from 010
      memory[25] = 8'd25; // Valor para comparación EQUAL 
      // Espacios en 0 hasta memory[31] 
    end




    always @(posedge clock) begin          //Logica para escribir en la memoria ram, se debe sincronizar con el clock
	    if (request_ram && reset && mem_control == 1'b0) begin
		    memory[mem_addr[5:0]] <= mem_data_out;  //Escribe lo que viene de mem_data_our en la direccion de memoria mem_addr 
	    end
    end


    always @(*) begin     //Logica para leer de la memoria ram, no requiere sincronizar el clock
      if (request_ram && reset && mem_control == 1'b1) begin     //Solo si ambos son verdaderos
          mem_data_in = memory[mem_addr[5:0]];     //Lee con mem_data_in lo que esta en la direccion mem_addr
        end
        else begin
		mem_data_in = 8'b0;
	end
    end




endmodule

Tarea 1/src/rom.v
module rom (/*AUTOARG*/
    // Inputs
   clock, reset, request_rom, prog_addr,
  

   // Outputs
   data, opcode, ab_select, op_addr
   );

   //Inputs 
   input clock, reset, request_rom;
   input [11:0] prog_addr;

   //Outputs
   output reg [12:0] data;
   output [3:0] opcode;
   output ab_select;
   output [7:0] op_addr; 

   // Memoria para almacenar las instrucciones
    reg [12:0] rom_memory [0:31];
	
   // Asignacion de salidas 
    assign opcode = data[12:9];
    assign ab_select = data[8];   
    assign op_addr  = data[7:0];

  // Initial block para inicializar y cambiar después de cierto tiempo
  initial begin
     // Programa de ejemplo de la Tabla #2
    rom_memory[0] = 13'b0011_0_00000101; // LOAD A from 005   Formato de instruccion "13'b operacion_a/b_direccion de la RAM" 
    rom_memory[1] = 13'b0011_1_00001010; // LOAD B from 010
    rom_memory[2] = 13'b1001_1_00000000; // ADD A+B in B
    rom_memory[3] = 13'b0100_0_00001111; // STORE A at 015
    rom_memory[4] = 13'b0100_1_00010100; // STORE B at 020
    rom_memory[5] = 13'b0011_0_00010100; // LOAD A from 020
    rom_memory[6] = 13'b0011_1_00011001; // LOAD B from 025
    rom_memory[7] = 13'b0101_0_00000000; // Equal A to B
    #940
    // Prueba con resta (Sub) y AND logica
    rom_memory[0] = 13'b0011_0_00000000; // Load A from 000 (primer digito del carnet)
    rom_memory[1] = 13'b0011_1_00000001; // Load B from 001 (segundo digito del carnet)
    rom_memory[2] = 13'b1010_0_00000000; // Sub A=A-B
    rom_memory[3] = 13'b0010_1_00000000; // AND B=A&B
    rom_memory[4] = 13'b0101_1_00000000; // Equal A to B 
    #940
    // Prueba con OR logica
    rom_memory[0] = 13'b0011_0_00000010; // LOAD A from 002 (tercer digito del carnet)
    rom_memory[1] = 13'b0011_1_00000011; // LOAD B from 003 (cuarto digito del carnet)
    rom_memory[2] = 13'b0001_0_00000000; // OR A=A|B 
    rom_memory[3] = 13'b0100_0_00011100; // STORE A on 028 
    rom_memory[4] = 13'b0101_0_00000000; // Equal A to B 
  end


  //always @(*) begin
	  //if (request_rom && reset && prog_addr < 16) begin
		//data = rom_memory[prog_addr];
	  //end
          //else begin
	     //data = 13'b0;
	  //end
  //end
  
  always @(posedge clock) begin
    if (!reset) begin // O 'rst' según tu nombre de señal
        data <= 13'b0;
    end else if (request_rom) begin
        // Verificamos que no exceda el tamaño del arreglo
        if (prog_addr < 20) 
            data <= rom_memory[prog_addr];
        else
            data <= 13'b0;
    end else begin
        data <= 13'b0;
    end
  end


endmodule

Tarea 1/src/testbench.v
`include "rom.v"
`include "ram.v"
`include "cmos_cells.v"
`include "tester.v"
`include "cpu.v"

module cpu_tb;
    
    // Wires
    wire clock;
    wire reset;
    wire ab_select;
    wire mem_control;
    wire equal;
    wire request_rom;
    wire request_ram;
    wire [12:0] data;
    wire [11:0] mem_addr;
    wire [7:0] mem_data_out;
    wire [7:0] mem_data_in;
    wire [7:0] op_addr;
    wire [3:0] opcode;
    wire [11:0] prog_addr;

    initial begin 
        $dumpfile("resultados.vcd");  // Nombre del archivo generado 
        $dumpvars(0, cpu_tb);  
    end

    // Instancia de ROM
    rom u_rom (
        .clock         (clock),
        .reset         (reset),
        .request_rom   (request_rom),
        .prog_addr     (prog_addr),
        .data          (data),
        .opcode        (opcode),
        .ab_select     (ab_select),
        .op_addr       (op_addr)
    );

    // Instancia de RAM
    ram u_ram (
        .clock        (clock),
        .reset        (reset),
        .request_ram  (request_ram),
        .mem_control  (mem_control),
        .mem_addr     (mem_addr),
        .mem_data_out (mem_data_out),
        .mem_data_in  (mem_data_in)
    );

    // Instancia de CPU
    cpu u_cpu (
        .clock        (clock),
        .reset        (reset),
        .opcode       (opcode),
        .ab_select    (ab_select),
        .op_addr      (op_addr),
        .mem_data_in  (mem_data_in),
        .prog_addr    (prog_addr),
        .mem_control  (mem_control),
        .mem_addr     (mem_addr),
        .equal        (equal),
        .request_rom  (request_rom),
        .request_ram  (request_ram),
        .mem_data_out (mem_data_out)
    );

    // Instancia de Tester
    tester u_tester (
        .clock   (clock),
        .reset   (reset)
    );

endmodule

Tarea 1/src/resultados.vcd
$date
	Sat May  2 09:46:55 2026
$end
$version
	Icarus Verilog
$end
$timescale
	1s
$end
$scope module cpu_tb $end
$var wire 1 ! reset $end
$var wire 1 " request_rom $end
$var wire 1 # request_ram $end
$var wire 12 $ prog_addr [11:0] $end
$var wire 4 % opcode [3:0] $end
$var wire 8 & op_addr [7:0] $end
$var wire 8 ' mem_data_out [7:0] $end
$var wire 8 ( mem_data_in [7:0] $end
$var wire 1 ) mem_control $end
$var wire 12 * mem_addr [11:0] $end
$var wire 1 + equal $end
$var wire 13 , data [12:0] $end
$var wire 1 - clock $end
$var wire 1 . ab_select $end
$scope module u_cpu $end
$var wire 1 ! reset $end
$var wire 4 / opcode [3:0] $end
$var wire 8 0 op_addr [7:0] $end
$var wire 8 1 mem_data_in [7:0] $end
$var wire 1 - clock $end
$var wire 1 . ab_select $end
$var parameter 4 2 End $end
$var parameter 4 3 Instruction $end
$var parameter 4 4 add $end
$var parameter 4 5 and_ $end
$var parameter 4 6 equal_operation $end
$var parameter 4 7 load $end
$var parameter 4 8 load_register $end
$var parameter 4 9 logic_operation $end
$var parameter 4 : or_ $end
$var parameter 4 ; read_ROM $end
$var parameter 4 < send_ROM $end
$var parameter 4 = store $end
$var parameter 4 > sub $end
$var parameter 4 ? wait_RAM $end
$var parameter 4 @ wait_ROM $end
$var reg 8 A A [7:0] $end
$var reg 8 B B [7:0] $end
$var reg 1 + equal $end
$var reg 1 C equal_next $end
$var reg 12 D mem_addr [11:0] $end
$var reg 12 E mem_addr_next [11:0] $end
$var reg 1 ) mem_control $end
$var reg 1 F mem_control_next $end
$var reg 8 G mem_data_out [7:0] $end
$var reg 8 H mem_data_out_next [7:0] $end
$var reg 8 I next_A [7:0] $end
$var reg 8 J next_B [7:0] $end
$var reg 4 K next_state [3:0] $end
$var reg 12 L prog_addr [11:0] $end
$var reg 12 M prog_addr_next [11:0] $end
$var reg 1 N reg_ab_select $end
$var reg 1 O reg_ab_select_next $end
$var reg 8 P reg_op_addr [7:0] $end
$var reg 8 Q reg_op_addr_next [7:0] $end
$var reg 4 R reg_opcode [3:0] $end
$var reg 4 S reg_opcode_next [3:0] $end
$var reg 1 # request_ram $end
$var reg 1 T request_ram_next $end
$var reg 1 " request_rom $end
$var reg 1 U request_rom_next $end
$var reg 4 V state [3:0] $end
$upscope $end
$scope module u_ram $end
$var wire 12 W mem_addr [11:0] $end
$var wire 1 ) mem_control $end
$var wire 8 X mem_data_out [7:0] $end
$var wire 1 # request_ram $end
$var wire 1 ! reset $end
$var wire 1 - clock $end
$var parameter 32 Y read $end
$var parameter 32 Z write $end
$var reg 8 [ mem_data_in [7:0] $end
$var integer 32 \ i [31:0] $end
$upscope $end
$scope module u_rom $end
$var wire 12 ] prog_addr [11:0] $end
$var wire 1 " request_rom $end
$var wire 1 ! reset $end
$var wire 4 ^ opcode [3:0] $end
$var wire 8 _ op_addr [7:0] $end
$var wire 1 - clock $end
$var wire 1 . ab_select $end
$var reg 13 ` data [12:0] $end
$upscope $end
$scope module u_tester $end
$var reg 1 - clock $end
$var reg 1 ! reset $end
$upscope $end
$upscope $end
$enddefinitions $end
$comment Show the parameter values. $end
$dumpall
b0 Z
b1 Y
b1 @
b101 ?
b1010 >
b100 =
b0 <
b10 ;
b1 :
b11 9
b110 8
b11 7
b101 6
b10 5
b1001 4
b100 3
b111 2
$end
#0
$dumpvars
bx `
bx _
bx ^
bx ]
b100000 \
b0 [
bx X
bx W
bx V
0U
0T
bx S
bx R
bx Q
bx P
xO
xN
bx M
bx L
b0 K
bx J
bx I
bx H
bx G
xF
bx E
bx D
xC
bx B
bx A
b0 1
bx 0
bx /
x.
0-
bx ,
x+
bx *
x)
b0 (
bx '
bx &
bx %
bx $
x#
x"
0!
$end
#10
b0 %
b0 /
b0 ^
0.
b0 &
b0 0
b0 _
b1 K
1U
b0 ,
b0 `
0#
0"
b0 V
1-
1!
#20
0-
#30
b0 M
0C
b0 Q
0O
b0 S
1U
b0 H
b0 E
0F
b0 J
b0 I
b1 K
b0 P
0N
b0 R
b0 B
b0 A
0+
b0 '
b0 G
b0 X
b0 *
b0 D
b0 W
0)
b0 $
b0 L
b0 ]
1-
0!
#40
0-
1!
#50
b10 K
1U
1"
b1 V
1-
#60
0-
#70
b100 K
b101 Q
b11 S
0U
b11 %
b11 /
b11 ^
b101 &
b101 0
b101 _
b10 V
b11000000101 ,
b11000000101 `
1-
#80
0-
#90
b101 K
1F
b101 E
1T
b101 P
b11 R
0"
b100 V
1-
#100
0-
#110
b1100 (
b1100 1
b1100 [
b110 K
1T
b0 %
b0 /
b0 ^
b0 &
b0 0
b0 _
1#
b101 *
b101 D
b101 W
1)
b101 V
b0 ,
b0 `
1-
#120
0-
#130
b1 M
b0 K
b1100 I
0T
b110 V
1-
#140
0-
#150
b0 (
b0 1
b0 [
b1 K
1U
b1 $
b1 L
b1 ]
0#
b1100 A
b0 V
1-
#160
0-
#170
b10 K
1U
1"
b1 V
1-
#180
0-
#190
b100 K
b1010 Q
1O
0U
b11 %
b11 /
b11 ^
1.
b1010 &
b1010 0
b1010 _
b10 V
b11100001010 ,
b11100001010 `
1-
#200
0-
#210
b101 K
b1010 E
1T
b1010 P
1N
0"
b100 V
1-
#220
0-
#230
b1101 (
b1101 1
b1101 [
b110 K
1T
b0 %
b0 /
b0 ^
0.
b0 &
b0 0
b0 _
1#
b1010 *
b1010 D
b1010 W
b101 V
b0 ,
b0 `
1-
#240
0-
#250
b10 M
b0 K
b1101 J
0T
b110 V
1-
#260
0-
#270
b0 (
b0 1
b0 [
b1 K
1U
b10 $
b10 L
b10 ]
0#
b1101 B
b0 V
1-
#280
0-
#290
b10 K
1U
1"
b1 V
1-
#300
0-
#310
b11 K
b0 Q
b1001 S
0U
b1001 %
b1001 /
b1001 ^
1.
b10 V
b1001100000000 ,
b1001100000000 `
1-
#320
0-
#330
b11 M
b0 K
b11001 I
b0 P
b1001 R
0"
b11 V
1-
#340
0-
#350
b1 K
1U
b0 %
b0 /
b0 ^
0.
b11 $
b11 L
b11 ]
b11001 A
b0 V
b0 ,
b0 `
1-
#360
0-
#370
b10 K
1U
1"
b1 V
1-
#380
0-
#390
b100 K
b1111 Q
0O
b100 S
0U
b100 %
b100 /
b100 ^
b1111 &
b1111 0
b1111 _
b10 V
b100000001111 ,
b100000001111 `
1-
#400
0-
#410
b101 K
b11001 H
0F
b1111 E
1T
b1111 P
0N
b100 R
0"
b100 V
1-
#420
0-
#430
b100 M
b0 K
1T
b0 %
b0 /
b0 ^
b0 &
b0 0
b0 _
1#
b11001 '
b11001 G
b11001 X
b1111 *
b1111 D
b1111 W
0)
b101 V
b0 ,
b0 `
1-
#440
0-
#450
b1 K
1U
0T
b100 $
b100 L
b100 ]
b0 V
1-
#460
0-
#470
b10 K
1U
0#
1"
b1 V
1-
#480
0-
#490
1O
b100 %
b100 /
b100 ^
1.
b10100 &
b10100 0
b10100 _
b100 K
b10100 Q
b100 S
0U
b100100010100 ,
b100100010100 `
b10 V
1-
#500
0-
#510
b101 K
b1101 H
b10100 E
1T
b10100 P
1N
0"
b100 V
1-
#520
0-
#530
b0 %
b0 /
b0 ^
0.
b0 &
b0 0
b0 _
b101 M
b0 K
1T
b0 ,
b0 `
1#
b1101 '
b1101 G
b1101 X
b10100 *
b10100 D
b10100 W
b101 V
1-
#540
0-
#550
b1 K
1U
0T
b101 $
b101 L
b101 ]
b0 V
1-
#560
0-
#570
b10 K
1U
0#
1"
b1 V
1-
#580
0-
#590
b100 K
0O
b11 S
0U
b11 %
b11 /
b11 ^
b10100 &
b10100 0
b10100 _
b10 V
b11000010100 ,
b11000010100 `
1-
#600
0-
#610
b101 K
1F
1T
0N
b11 R
0"
b100 V
1-
#620
0-
#630
b1101 (
b1101 1
b1101 [
b110 K
1T
b0 %
b0 /
b0 ^
b0 &
b0 0
b0 _
1#
1)
b101 V
b0 ,
b0 `
1-
#640
0-
#650
b110 M
b0 K
b1101 I
0T
b110 V
1-
#660
0-
#670
b0 (
b0 1
b0 [
b1 K
1U
b110 $
b110 L
b110 ]
0#
b1101 A
b0 V
1-
#680
0-
#690
b10 K
1U
1"
b1 V
1-
#700
0-
#710
b100 K
b11001 Q
1O
0U
b11 %
b11 /
b11 ^
1.
b11001 &
b11001 0
b11001 _
b10 V
b11100011001 ,
b11100011001 `
1-
#720
0-
#730
b101 K
b11001 E
1T
b11001 P
1N
0"
b100 V
1-
#740
0-
#750
b11001 (
b11001 1
b11001 [
b110 K
1T
b0 %
b0 /
b0 ^
0.
b0 &
b0 0
b0 _
1#
b11001 *
b11001 D
b11001 W
b101 V
b0 ,
b0 `
1-
#760
0-
#770
b111 M
b0 K
b11001 J
0T
b110 V
1-
#780
0-
#790
b0 (
b0 1
b0 [
b1 K
1U
b111 $
b111 L
b111 ]
0#
b11001 B
b0 V
1-
#800
0-
#810
b10 K
1U
1"
b1 V
1-
#820
0-
#830
b11 K
b0 Q
0O
b101 S
0U
b101 %
b101 /
b101 ^
b10 V
b101000000000 ,
b101000000000 `
1-
#840
0-
#850
b111 K
b0 P
0N
b101 R
0"
b11 V
1-
#860
0-
#870
b0 %
b0 /
b0 ^
b111 V
b0 ,
b0 `
1-
#880
0-
#890
1-
#900
0-
#910
1-
#920
0-
#930
1-
#940
0-
#950
1-
#960
0-
#970
1-
#980
0-
#990
1U
b0 M
b0 S
b0 H
b0 E
0F
b0 J
b0 I
b1 K
b0 R
b0 B
b0 A
b0 '
b0 G
b0 X
b0 *
b0 D
b0 W
0)
b0 $
b0 L
b0 ]
b0 V
1-
0!
#1000
0-
1!
#1010
b10 K
1U
1"
b1 V
1-
#1020
0-
#1030
b100 K
b11 S
0U
b11 %
b11 /
b11 ^
b10 V
b11000000000 ,
b11000000000 `
1-
#1040
0-
#1050
b101 K
1F
1T
b11 R
0"
b100 V
1-
#1060
0-
#1070
b111 (
b111 1
b111 [
b110 K
1T
b0 %
b0 /
b0 ^
1#
1)
b101 V
b0 ,
b0 `
1-
#1080
0-
#1090
b1 M
b0 K
b111 I
0T
b110 V
1-
#1100
0-
#1110
b0 (
b0 1
b0 [
b1 K
1U
b1 $
b1 L
b1 ]
0#
b111 A
b0 V
1-
#1120
0-
#1130
b10 K
1U
1"
b1 V
1-
#1140
0-
#1150
b100 K
b1 Q
1O
0U
b11 %
b11 /
b11 ^
1.
b1 &
b1 0
b1 _
b10 V
b11100000001 ,
b11100000001 `
1-
#1160
0-
#1170
b101 K
b1 E
1T
b1 P
1N
0"
b100 V
1-
#1180
0-
#1190
b110 (
b110 1
b110 [
b110 K
1T
b0 %
b0 /
b0 ^
0.
b0 &
b0 0
b0 _
1#
b1 *
b1 D
b1 W
b101 V
b0 ,
b0 `
1-
#1200
0-
#1210
b10 M
b0 K
b110 J
0T
b110 V
1-
#1220
0-
#1230
b0 (
b0 1
b0 [
b1 K
1U
b10 $
b10 L
b10 ]
0#
b110 B
b0 V
1-
#1240
0-
#1250
b10 K
1U
1"
b1 V
1-
#1260
0-
#1270
b11 K
b0 Q
0O
b1010 S
0U
b1010 %
b1010 /
b1010 ^
b10 V
b1010000000000 ,
b1010000000000 `
1-
#1280
0-
#1290
b11 M
b0 K
b1 J
b0 P
0N
b1010 R
0"
b11 V
1-
#1300
0-
#1310
b1 K
1U
b0 %
b0 /
b0 ^
b11 $
b11 L
b11 ]
b1 B
b0 V
b0 ,
b0 `
1-
#1320
0-
#1330
b10 K
1U
1"
b1 V
1-
#1340
0-
#1350
b11 K
1O
b10 S
0U
b10 %
b10 /
b10 ^
1.
b10 V
b10100000000 ,
b10100000000 `
1-
#1360
0-
#1370
b100 M
b0 K
b1 I
1N
b10 R
0"
b11 V
1-
#1380
0-
#1390
b1 K
1U
b0 %
b0 /
b0 ^
0.
b100 $
b100 L
b100 ]
b1 A
b0 V
b0 ,
b0 `
1-
#1400
0-
#1410
b10 K
1U
1"
b1 V
1-
#1420
0-
#1430
b11 K
b101 S
0U
b101 %
b101 /
b101 ^
1.
b10 V
b101100000000 ,
b101100000000 `
1-
#1440
0-
#1450
b111 K
1C
b101 R
0"
b11 V
1-
#1460
0-
#1470
b0 %
b0 /
b0 ^
0.
1+
b111 V
b0 ,
b0 `
1-
#1480
0-
#1490
1-
#1500
0-
#1510
1-
#1520
0-
#1530
1-
#1540
0-
#1550
1-
#1560
0-
#1570
1-
#1580
0-
#1590
1-
#1600
0-
#1610
1-
#1620
0-
#1630
1-
#1640
0-
#1650
1U
b0 M
0C
0O
b0 S
b0 E
0F
b0 J
b0 I
b1 K
0N
b0 R
b0 B
b0 A
0+
b0 *
b0 D
b0 W
0)
b0 $
b0 L
b0 ]
b0 V
1-
0!
#1660
0-
1!
#1670
b10 K
1U
1"
b1 V
1-
#1680
0-
#1690
b11 S
b11 %
b11 /
b11 ^
b100 K
0U
b11000000000 ,
b11000000000 `
b10 V
1-
#1700
0-
#1710
b101 K
1F
1T
b11 R
0"
b100 V
1-
#1720
0-
#1730
b0 %
b0 /
b0 ^
b111 (
b111 1
b111 [
b110 K
1T
b0 ,
b0 `
1#
1)
b101 V
1-
#1740
0-
#1750
b1 M
b0 K
b111 I
0T
b110 V
1-
#1760
0-
#1770
b0 (
b0 1
b0 [
b1 K
1U
b1 $
b1 L
b1 ]
0#
b111 A
b0 V
1-
#1780
0-
#1790
b10 K
1U
1"
b1 V
1-
#1800
0-
#1810
b1 Q
1O
b11 %
b11 /
b11 ^
1.
b1 &
b1 0
b1 _
b100 K
b11 S
0U
b11100000001 ,
b11100000001 `
b10 V
1-
#1820
0-
#1830
b101 K
b1 E
1T
b1 P
1N
0"
b100 V
1-
#1840
0-
#1850
b0 %
b0 /
b0 ^
0.
b0 &
b0 0
b0 _
b110 (
b110 1
b110 [
b110 K
1T
b0 ,
b0 `
1#
b1 *
b1 D
b1 W
b101 V
1-
#1860
0-
#1870
b10 M
b0 K
b110 J
0T
b110 V
1-
#1880
0-
#1890
b0 (
b0 1
b0 [
b1 K
1U
b10 $
b10 L
b10 ]
0#
b110 B
b0 V
1-
#1900
0-
#1910
b10 K
1U
1"
b1 V
1-
#1920
0-
#1930
b1 %
b1 /
b1 ^
b11 K
b0 Q
0O
b1 S
0U
b1000000000 ,
b1000000000 `
b10 V
1-
#1940
0-
#1950
b11 M
b0 K
b111 J
b0 P
0N
b1 R
0"
b11 V
1-
#1960
0-
#1970
b0 %
b0 /
b0 ^
b1 K
1U
b0 ,
b0 `
b11 $
b11 L
b11 ]
b111 B
b0 V
1-
#1980
0-
#1990
b10 K
1U
1"
b1 V
1-
#2000
0-
#2010
b11100 Q
b100 %
b100 /
b100 ^
b11100 &
b11100 0
b11100 _
b100 K
b100 S
0U
b100000011100 ,
b100000011100 `
b10 V
1-
#2020
0-
#2030
b101 K
b111 H
0F
b11100 E
1T
b11100 P
b100 R
0"
b100 V
1-
#2040
0-
#2050
b0 %
b0 /
b0 ^
b0 &
b0 0
b0 _
b100 M
b0 K
1T
b0 ,
b0 `
1#
b111 '
b111 G
b111 X
b11100 *
b11100 D
b11100 W
0)
b101 V
1-
#2060
0-
#2070
b1 K
1U
0T
b100 $
b100 L
b100 ]
b0 V
1-
#2080
0-
#2090
b10 K
1U
0#
1"
b1 V
1-
#2100
0-
#2110
b11 K
b0 Q
b101 S
0U
b101 %
b101 /
b101 ^
b10 V
b101000000000 ,
b101000000000 `
1-
#2120
0-
#2130
b111 K
1C
b0 P
b101 R
0"
b11 V
1-
#2140
0-
#2150
b0 %
b0 /
b0 ^
1+
b111 V
b0 ,
b0 `
1-
